callsign.py
callsign-0.1.0.dist-info/METADATA
callsign-0.1.0.dist-info/WHEEL
callsign-0.1.0.dist-info/licenses/LICENSE
callsign-0.1.0.dist-info/RECORD
