Metadata-Version: 2.3
Name: callsign
Version: 0.1.0
Summary: Simplified Introspection
Project-URL: repository, https://github.com/muhamuhamuha/callsign
Author: muhamuhamuha
License-Expression: MIT
License-File: LICENSE
Keywords: ddd,decorator,decorator driven development,function,introspection,metaprogramming,signature
Classifier: Development Status :: 5 - Production/Stable
Classifier: Intended Audience :: Developers
Classifier: License :: OSI Approved :: MIT License
Classifier: Natural Language :: English
Classifier: Operating System :: OS Independent
Classifier: Programming Language :: Python :: 3.7
Classifier: Programming Language :: Python :: 3.8
Classifier: Programming Language :: Python :: 3.9
Classifier: Programming Language :: Python :: 3.10
Classifier: Programming Language :: Python :: 3.11
Classifier: Programming Language :: Python :: 3.12
Classifier: Programming Language :: Python :: Implementation :: CPython
Classifier: Programming Language :: Python :: Implementation :: PyPy
Requires-Python: >=3.8
Provides-Extra: dev
Requires-Dist: pytest; extra == 'dev'
